HW10/Source/OL.v
module OL(
    input [3:0] CurrentState,
    output reg [9:0] LEDR
);

parameter ZERO_B = 0;
parameter ONE_B = 9'b0_0000_0001;
parameter TWO_B = 9'b0_0000_0010;
parameter THREE_B = 9'b0_0000_0011;
parameter FIVE_B = 9'b0_0000_0101;
parameter EIGHT_B = 9'b0_0000_1000;
parameter THIRTEEN = 9'b0_0000_1101;
parameter TWENTY_ONE = 9'b0_0001_0101;
parameter THIRTY_FOUR = 9'b0_0010_0010;

parameter ZERO = 4'b0000;
parameter ONE = 4'b0001;
parameter TWO = 4'b0010;
parameter THREE = 4'b0011;
parameter FOUR = 4'b0100;
parameter FIVE = 4'b0101;
parameter SIX = 4'b0110;
parameter SEVEN = 4'b0111;
parameter EIGHT = 4'b1000;



always@(*)begin
    case(CurrentState)
    ZERO : LEDR = ZERO_B;
    ONE : LEDR = ONE_B;
    TWO : LEDR = TWO_B;
    THREE : LEDR = THREE_B;
    FOUR : LEDR = FIVE_B;
    FIVE : LEDR = EIGHT_B;
    SIX : LEDR = THIRTEEN;
    SEVEN : LEDR = TWENTY_ONE;
    EIGHT: LEDR = THIRTY_FOUR;
    default: LEDR = ZERO_B;
    endcase
end

endmodule

HW10/Source/NSL.v
module NSL(
    input [3:0] CurrentState,
    output reg [3:0] NextState
);
parameter ZERO = 4'b0000;
parameter ONE = 4'b0001;
parameter TWO = 4'b0010;
parameter THREE = 4'b0011;
parameter FOUR = 4'b0100;
parameter FIVE = 4'b0101;
parameter SIX = 4'b0110;
parameter SEVEN = 4'b0111;
parameter EIGHT = 4'b1000;

always@(*)
begin
    case(CurrentState)
        ZERO : NextState = ONE;
        ONE : NextState = TWO;
        TWO : NextState = THREE;
        THREE : NextState = FOUR;
        FOUR : NextState = FIVE;
        FIVE : NextState = SIX;
        SIX : NextState = SEVEN;
        SEVEN : NextState = EIGHT;
        EIGHT: NextState = ZERO;
        default: NextState = ZERO;
    endcase
end


endmodule

Project3/Source/CSL.v
module CSL(
input clock,reset_n,
input [3:0] NextState,
output reg [3:0] CurrentState
);


always @(posedge clock, negedge reset_n ) begin
    if (reset_n == 0) begin
        CurrentState <= 0;
    end
    else 
        CurrentState <= NextState;
end
endmodule

HW10/Source/tb_State.v
`timescale 1 ns / 100 ps
module tb_State();

reg clock = 0;
reg reset_n;

wire [9:0] LEDR;
wire [3:0] CurrentState, NextState;

always #10 clock = ~clock;

CSL CS (.clock(clock),.reset_n(reset_n),.CurrentState(CurrentState),.NextState(NextState));
NSL NS (.CurrentState(CurrentState),.NextState(NextState));
OL O (.LEDR(LEDR),.CurrentState(CurrentState));

initial
begin
    $dumpfile("tb_State.vcd");
    $dumpvars;
    reset_n = 0;
    #20 reset_n = 1;

    #300;
    #20 reset_n =0;
    #20 $finish;
    
end
initial begin
    $monitor($time, " CurrentState = %d , NextState = %d , LEDR = %d", CurrentState,NextState, LEDR);
end



endmodule

HW10/Source/tb_State.vcd
$date
	Mon Nov 02 08:57:43 2020
$end
$version
	Icarus Verilog
$end
$timescale
	100ps
$end
$scope module tb_State $end
$var wire 4 ! NextState [3:0] $end
$var wire 10 " LEDR [9:0] $end
$var wire 4 # CurrentState [3:0] $end
$var reg 1 $ clock $end
$var reg 1 % reset_n $end
$scope module CS $end
$var wire 1 $ clock $end
$var wire 1 % reset_n $end
$var wire 4 & NextState [3:0] $end
$var reg 4 ' CurrentState [3:0] $end
$upscope $end
$scope module NS $end
$var wire 4 ( CurrentState [3:0] $end
$var reg 4 ) NextState [3:0] $end
$upscope $end
$scope module O $end
$var wire 4 * CurrentState [3:0] $end
$var reg 10 + LEDR [9:0] $end
$upscope $end
$upscope $end
$enddefinitions $end
#0
$dumpvars
b0 +
b0 *
b1 )
b0 (
b0 '
b1 &
0%
0$
b0 #
b0 "
b1 !
$end
#100
1$
#200
0$
1%
#300
b10 !
b10 &
b10 )
b1 "
b1 +
b1 #
b1 '
b1 (
b1 *
1$
#400
0$
#500
b10 "
b10 +
b11 !
b11 &
b11 )
b10 #
b10 '
b10 (
b10 *
1$
#600
0$
#700
b100 !
b100 &
b100 )
b11 "
b11 +
b11 #
b11 '
b11 (
b11 *
1$
#800
0$
#900
b101 "
b101 +
b101 !
b101 &
b101 )
b100 #
b100 '
b100 (
b100 *
1$
#1000
0$
#1100
b110 !
b110 &
b110 )
b1000 "
b1000 +
b101 #
b101 '
b101 (
b101 *
1$
#1200
0$
#1300
b1101 "
b1101 +
b111 !
b111 &
b111 )
b110 #
b110 '
b110 (
b110 *
1$
#1400
0$
#1500
b1000 !
b1000 &
b1000 )
b10101 "
b10101 +
b111 #
b111 '
b111 (
b111 *
1$
#1600
0$
#1700
b100010 "
b100010 +
b0 !
b0 &
b0 )
b1000 #
b1000 '
b1000 (
b1000 *
1$
#1800
0$
#1900
b1 !
b1 &
b1 )
b0 "
b0 +
b0 #
b0 '
b0 (
b0 *
1$
#2000
0$
#2100
b1 "
b1 +
b10 !
b10 &
b10 )
b1 #
b1 '
b1 (
b1 *
1$
#2200
0$
#2300
b11 !
b11 &
b11 )
b10 "
b10 +
b10 #
b10 '
b10 (
b10 *
1$
#2400
0$
#2500
b11 "
b11 +
b100 !
b100 &
b100 )
b11 #
b11 '
b11 (
b11 *
1$
#2600
0$
#2700
b101 !
b101 &
b101 )
b101 "
b101 +
b100 #
b100 '
b100 (
b100 *
1$
#2800
0$
#2900
b1000 "
b1000 +
b110 !
b110 &
b110 )
b101 #
b101 '
b101 (
b101 *
1$
#3000
0$
#3100
b111 !
b111 &
b111 )
b1101 "
b1101 +
b110 #
b110 '
b110 (
b110 *
1$
#3200
0$
#3300
b10101 "
b10101 +
b1000 !
b1000 &
b1000 )
b111 #
b111 '
b111 (
b111 *
1$
#3400
b1 !
b1 &
b1 )
b0 "
b0 +
b0 #
b0 '
b0 (
b0 *
0$
0%
