Project2/Source/DDMM1.v
module DDMM1(
input wire  [3:0] MSB,LSB,
//input  clock, reset_n,
input [9:0] SW,
output reg[4:0] DD,
output reg[3:0] MM,MM_MSB

);
wire [7:0] binary_value;
assign binary_value = (MSB[3:0]*10)+({4'b0,LSB[3:0]});   // 4 bits to decimal



wire leap_year;
assign leap_year = SW[9];


always@(*)
begin
    
     if (binary_value <= 31) begin          // January
        MM <= 1;
        DD <= binary_value; // 
        MM_MSB = 0;
    end
    else if (binary_value <= 31+28+leap_year) begin  //Feb
        MM <= 2;
        DD <= binary_value - 31;
        MM_MSB = 0;
    end
    else if (binary_value <= 31+28+leap_year+31) begin // March
        MM <= 3;
        DD <= binary_value - 31-28-leap_year;
        MM_MSB = 0;
    end
    else  begin                                         // April
        MM <= 4;
        DD <= binary_value-31-28-leap_year-31;
        MM_MSB = 0;
    end
end



endmodule

Project2/Source/DD_MSB_LSB.v
module DD_MSB_LSB(
input [4:0] DD,
output reg [3:0] DD_MSB,DD_LSB

);


always@(DD)
begin
    if (DD < 10) begin
        DD_MSB = 0;
        DD_LSB = DD;
    end

    else if (DD< 20)begin
        DD_MSB = 1;
        DD_LSB = DD-10 ;
    end
    else if (DD <30) begin
        DD_MSB = 2;
        DD_LSB = DD-20;

    end  
    else 
    begin
        DD_MSB = 3;
        DD_LSB = DD-30;
    end 
end



endmodule

Project2/Source/counterBCD.v
module counterBCD(
    input clock, reset_n,
    output reg [3:0] countLSB, countMSB
    //output wire [7:0] HEX5,HEX4
);


always @(posedge clock, negedge reset_n ) 
begin
    if (reset_n == 0)
        begin
            countLSB <= 1;             // Reset LEB = 1
            countMSB <= 0;             // Reset MSB = 0;
        end
    
    else if (countLSB != 9) 
        begin
            countLSB <= countLSB + 1;       //LSB counter
        end
    else if (countMSB == 9 && countLSB==9 )         // Roll over / same as reset 
        begin
            countLSB <= 1;
            countMSB <= 0;
        end
            
    else
        begin
            if(countLSB == 9)begin              //MSB counter
                    countMSB <= countMSB+1;
                end
            countLSB <=0;                       // When LSB count to 9, roll over
                
               
        end    
end
endmodule

Project2/Source/tb_DDMM.v
`timescale 1 ns /  100 ps
module tb_DDMM();

reg clock =0;

 wire reset_n;
 reg [1:0] KEY;
 reg [9:0]  SW;

 wire [3:0] MSB,LSB; // day of years
 wire [3:0] MM,DD_MSB,DD_LSB,MM_MSB;
 wire [4:0] DD;
wire [7:0] binary_value;
assign binary_value = (MSB[3:0]*10)+({4'b0,LSB[3:0]}); 
counterBCD C1(.clock(clock),.reset_n(reset_n),.countMSB(MSB),.countLSB(LSB));

DD_MSB_LSB D2(.DD(DD),.DD_MSB(DD_MSB),.DD_LSB(DD_LSB));
DDMM1 D1(.MSB(MSB),.LSB(LSB),.DD(DD),.MM(MM),.SW(SW),.MM_MSB(MM_MSB));




assign reset_n = KEY[0]? KEY[0]:KEY[0];

always#10 clock = ~clock;

initial
	begin
		$dumpfile("tb_DDMM.vcd");
		$dumpvars;
		    KEY[0] = 0;			// Reset/ initialized MSB and LSB/ KEY[0] is pressed
			SW[9:0] = 10'b0;

		#10 KEY[0] = 1;				// KEY[0] is not pressed after 10ns delay
		#2200;						// clock 110
		
		
		
		#10 $finish;
	end


initial
begin
	$monitor($time, " binary_value = %d, DD = %d , DD_MSB = %d,   DD_LSB = %d , MM = %d", binary_value,DD, DD_MSB,DD_LSB,MM );
end	
endmodule

Project2/Source/decoder.v
module decoder(
    input [3:0] MSB,birth,
    output reg [7:0] HEX
);

always @(birth)
begin
    case(birth)
        4'b0000: HEX = (MSB == 4'b0000)? 8'b1111_1111:8'b1100_0000;
        4'b0001: HEX = 8'b1111_1001;    //1
        4'b0010: HEX = 8'b1010_0100;    //2
        4'b0011: HEX = 8'b1011_0000;    //3
        4'b0100: HEX = 8'b1001_1001;    //4
        4'b0101: HEX = 8'b1001_0010;    //5 
        4'b0110: HEX = 8'b1000_0010;    //6
        4'b0111: HEX = 8'b1111_1000;    //7
        4'b1000: HEX = 8'b1000_0000;    //8
        4'b1001: HEX = 8'b1001_1000;    //9
       
        default HEX= 8'b1111_1111;
    endcase
    
end


endmodule

Project2/TestbenchOutput/tb_DDMM.vcd
$date
	Fri Oct 23 17:57:06 2020
$end
$version
	Icarus Verilog
$end
$timescale
	100ps
$end
$scope module decoder $end
$var wire 4 ! MSB [3:0] $end
$var wire 4 " birth [3:0] $end
$var reg 8 # HEX [7:0] $end
$upscope $end
$scope module tb_DDMM $end
$var wire 1 $ reset_n $end
$var wire 8 % binary_value [7:0] $end
$var wire 4 & MSB [3:0] $end
$var wire 4 ' MM_MSB [3:0] $end
$var wire 4 ( MM [3:0] $end
$var wire 4 ) LSB [3:0] $end
$var wire 4 * DD_MSB [3:0] $end
$var wire 4 + DD_LSB [3:0] $end
$var wire 5 , DD [4:0] $end
$var reg 2 - KEY [1:0] $end
$var reg 10 . SW [9:0] $end
$var reg 1 / clock $end
$scope module C1 $end
$var wire 1 / clock $end
$var wire 1 $ reset_n $end
$var reg 4 0 countLSB [3:0] $end
$var reg 4 1 countMSB [3:0] $end
$upscope $end
$scope module D1 $end
$var wire 4 2 LSB [3:0] $end
$var wire 4 3 MSB [3:0] $end
$var wire 10 4 SW [9:0] $end
$var wire 1 5 leap_year $end
$var wire 8 6 binary_value [7:0] $end
$var reg 5 7 DD [4:0] $end
$var reg 4 8 MM [3:0] $end
$var reg 4 9 MM_MSB [3:0] $end
$upscope $end
$scope module D2 $end
$var wire 5 : DD [4:0] $end
$var reg 4 ; DD_LSB [3:0] $end
$var reg 4 < DD_MSB [3:0] $end
$upscope $end
$upscope $end
$enddefinitions $end
#0
$dumpvars
b0 <
b1 ;
b1 :
b0 9
b1 8
b1 7
b1 6
05
b0 4
b0 3
b1 2
b0 1
b1 0
0/
b0 .
bx0 -
b1 ,
b1 +
b0 *
b1 )
b1 (
b0 '
b0 &
b1 %
0$
b11111111 #
bz "
bz !
$end
#100
1$
bx1 -
1/
#200
0/
#300
b10 +
b10 ;
b10 ,
b10 7
b10 :
b10 6
b10 %
b10 )
b10 0
b10 2
1/
#400
0/
#500
b11 +
b11 ;
b11 ,
b11 7
b11 :
b11 6
b11 %
b11 )
b11 0
b11 2
1/
#600
0/
#700
b100 +
b100 ;
b100 ,
b100 7
b100 :
b100 6
b100 %
b100 )
b100 0
b100 2
1/
#800
0/
#900
b101 +
b101 ;
b101 ,
b101 7
b101 :
b101 6
b101 %
b101 )
b101 0
b101 2
1/
#1000
0/
#1100
b110 +
b110 ;
b110 ,
b110 7
b110 :
b110 6
b110 %
b110 )
b110 0
b110 2
1/
#1200
0/
#1300
b111 +
b111 ;
b111 ,
b111 7
b111 :
b111 6
b111 %
b111 )
b111 0
b111 2
1/
#1400
0/
#1500
b1000 +
b1000 ;
b1000 ,
b1000 7
b1000 :
b1000 6
b1000 %
b1000 )
b1000 0
b1000 2
1/
#1600
0/
#1700
b1001 +
b1001 ;
b1001 ,
b1001 7
b1001 :
b1001 6
b1001 %
b1001 )
b1001 0
b1001 2
1/
#1800
0/
#1900
b0 +
b0 ;
b1 *
b1 <
b1010 ,
b1010 7
b1010 :
b0 )
b0 0
b0 2
b1010 6
b1010 %
b1 &
b1 1
b1 3
1/
#2000
0/
#2100
b1 +
b1 ;
b1011 ,
b1011 7
b1011 :
b1011 6
b1011 %
b1 )
b1 0
b1 2
1/
#2200
0/
#2300
b10 +
b10 ;
b1100 ,
b1100 7
b1100 :
b1100 6
b1100 %
b10 )
b10 0
b10 2
1/
#2400
0/
#2500
b11 +
b11 ;
b1101 ,
b1101 7
b1101 :
b1101 6
b1101 %
b11 )
b11 0
b11 2
1/
#2600
0/
#2700
b100 +
b100 ;
b1110 ,
b1110 7
b1110 :
b1110 6
b1110 %
b100 )
b100 0
b100 2
1/
#2800
0/
#2900
b101 +
b101 ;
b1111 ,
b1111 7
b1111 :
b1111 6
b1111 %
b101 )
b101 0
b101 2
1/
#3000
0/
#3100
b110 +
b110 ;
b10000 ,
b10000 7
b10000 :
b10000 6
b10000 %
b110 )
b110 0
b110 2
1/
#3200
0/
#3300
b111 +
b111 ;
b10001 ,
b10001 7
b10001 :
b10001 6
b10001 %
b111 )
b111 0
b111 2
1/
#3400
0/
#3500
b1000 +
b1000 ;
b10010 ,
b10010 7
b10010 :
b10010 6
b10010 %
b1000 )
b1000 0
b1000 2
1/
#3600
0/
#3700
b1001 +
b1001 ;
b10011 ,
b10011 7
b10011 :
b10011 6
b10011 %
b1001 )
b1001 0
b1001 2
1/
#3800
0/
#3900
b0 +
b0 ;
b10 *
b10 <
b10100 ,
b10100 7
b10100 :
b0 )
b0 0
b0 2
b10100 6
b10100 %
b10 &
b10 1
b10 3
1/
#4000
0/
#4100
b1 +
b1 ;
b10101 ,
b10101 7
b10101 :
b10101 6
b10101 %
b1 )
b1 0
b1 2
1/
#4200
0/
#4300
b10 +
b10 ;
b10110 ,
b10110 7
b10110 :
b10110 6
b10110 %
b10 )
b10 0
b10 2
1/
#4400
0/
#4500
b11 +
b11 ;
b10111 ,
b10111 7
b10111 :
b10111 6
b10111 %
b11 )
b11 0
b11 2
1/
#4600
0/
#4700
b100 +
b100 ;
b11000 ,
b11000 7
b11000 :
b11000 6
b11000 %
b100 )
b100 0
b100 2
1/
#4800
0/
#4900
b101 +
b101 ;
b11001 ,
b11001 7
b11001 :
b11001 6
b11001 %
b101 )
b101 0
b101 2
1/
#5000
0/
#5100
b110 +
b110 ;
b11010 ,
b11010 7
b11010 :
b11010 6
b11010 %
b110 )
b110 0
b110 2
1/
#5200
0/
#5300
b111 +
b111 ;
b11011 ,
b11011 7
b11011 :
b11011 6
b11011 %
b111 )
b111 0
b111 2
1/
#5400
0/
#5500
b1000 +
b1000 ;
b11100 ,
b11100 7
b11100 :
b11100 6
b11100 %
b1000 )
b1000 0
b1000 2
1/
#5600
0/
#5700
b1001 +
b1001 ;
b11101 ,
b11101 7
b11101 :
b11101 6
b11101 %
b1001 )
b1001 0
b1001 2
1/
#5800
0/
#5900
b0 +
b0 ;
b11 *
b11 <
b11110 ,
b11110 7
b11110 :
b0 )
b0 0
b0 2
b11110 6
b11110 %
b11 &
b11 1
b11 3
1/
#6000
0/
#6100
b1 +
b1 ;
b11111 ,
b11111 7
b11111 :
b11111 6
b11111 %
b1 )
b1 0
b1 2
1/
#6200
0/
#6300
b0 *
b0 <
b1 ,
b1 7
b1 :
b10 (
b10 8
b100000 6
b100000 %
b10 )
b10 0
b10 2
1/
#6400
0/
#6500
b10 +
b10 ;
b10 ,
b10 7
b10 :
b100001 6
b100001 %
b11 )
b11 0
b11 2
1/
#6600
0/
#6700
b11 +
b11 ;
b11 ,
b11 7
b11 :
b100010 6
b100010 %
b100 )
b100 0
b100 2
1/
#6800
0/
#6900
b100 +
b100 ;
b100 ,
b100 7
b100 :
b100011 6
b100011 %
b101 )
b101 0
b101 2
1/
#7000
0/
#7100
b101 +
b101 ;
b101 ,
b101 7
b101 :
b100100 6
b100100 %
b110 )
b110 0
b110 2
1/
#7200
0/
#7300
b110 +
b110 ;
b110 ,
b110 7
b110 :
b100101 6
b100101 %
b111 )
b111 0
b111 2
1/
#7400
0/
#7500
b111 +
b111 ;
b111 ,
b111 7
b111 :
b100110 6
b100110 %
b1000 )
b1000 0
b1000 2
1/
#7600
0/
#7700
b1000 +
b1000 ;
b1000 ,
b1000 7
b1000 :
b100111 6
b100111 %
b1001 )
b1001 0
b1001 2
1/
#7800
0/
#7900
b1001 +
b1001 ;
b1001 ,
b1001 7
b1001 :
b0 )
b0 0
b0 2
b101000 6
b101000 %
b100 &
b100 1
b100 3
1/
#8000
0/
#8100
b0 +
b0 ;
b1 *
b1 <
b1010 ,
b1010 7
b1010 :
b101001 6
b101001 %
b1 )
b1 0
b1 2
1/
#8200
0/
#8300
b1 +
b1 ;
b1011 ,
b1011 7
b1011 :
b101010 6
b101010 %
b10 )
b10 0
b10 2
1/
#8400
0/
#8500
b10 +
b10 ;
b1100 ,
b1100 7
b1100 :
b101011 6
b101011 %
b11 )
b11 0
b11 2
1/
#8600
0/
#8700
b11 +
b11 ;
b1101 ,
b1101 7
b1101 :
b101100 6
b101100 %
b100 )
b100 0
b100 2
1/
#8800
0/
#8900
b100 +
b100 ;
b1110 ,
b1110 7
b1110 :
b101101 6
b101101 %
b101 )
b101 0
b101 2
1/
#9000
0/
#9100
b101 +
b101 ;
b1111 ,
b1111 7
b1111 :
b101110 6
b101110 %
b110 )
b110 0
b110 2
1/
#9200
0/
#9300
b110 +
b110 ;
b10000 ,
b10000 7
b10000 :
b101111 6
b101111 %
b111 )
b111 0
b111 2
1/
#9400
0/
#9500
b111 +
b111 ;
b10001 ,
b10001 7
b10001 :
b110000 6
b110000 %
b1000 )
b1000 0
b1000 2
1/
#9600
0/
#9700
b1000 +
b1000 ;
b10010 ,
b10010 7
b10010 :
b110001 6
b110001 %
b1001 )
b1001 0
b1001 2
1/
#9800
0/
#9900
b1001 +
b1001 ;
b10011 ,
b10011 7
b10011 :
b0 )
b0 0
b0 2
b110010 6
b110010 %
b101 &
b101 1
b101 3
1/
#10000
0/
#10100
b0 +
b0 ;
b10 *
b10 <
b10100 ,
b10100 7
b10100 :
b110011 6
b110011 %
b1 )
b1 0
b1 2
1/
#10200
0/
#10300
b1 +
b1 ;
b10101 ,
b10101 7
b10101 :
b110100 6
b110100 %
b10 )
b10 0
b10 2
1/
#10400
0/
#10500
b10 +
b10 ;
b10110 ,
b10110 7
b10110 :
b110101 6
b110101 %
b11 )
b11 0
b11 2
1/
#10600
0/
#10700
b11 +
b11 ;
b10111 ,
b10111 7
b10111 :
b110110 6
b110110 %
b100 )
b100 0
b100 2
1/
#10800
0/
#10900
b100 +
b100 ;
b11000 ,
b11000 7
b11000 :
b110111 6
b110111 %
b101 )
b101 0
b101 2
1/
#11000
0/
#11100
b101 +
b101 ;
b11001 ,
b11001 7
b11001 :
b111000 6
b111000 %
b110 )
b110 0
b110 2
1/
#11200
0/
#11300
b110 +
b110 ;
b11010 ,
b11010 7
b11010 :
b111001 6
b111001 %
b111 )
b111 0
b111 2
1/
#11400
0/
#11500
b111 +
b111 ;
b11011 ,
b11011 7
b11011 :
b111010 6
b111010 %
b1000 )
b1000 0
b1000 2
1/
#11600
0/
#11700
b1000 +
b1000 ;
b11100 ,
b11100 7
b11100 :
b111011 6
b111011 %
b1001 )
b1001 0
b1001 2
1/
#11800
0/
#11900
b1 +
b1 ;
b0 *
b0 <
b1 ,
b1 7
b1 :
b11 (
b11 8
b0 )
b0 0
b0 2
b111100 6
b111100 %
b110 &
b110 1
b110 3
1/
#12000
0/
#12100
b10 +
b10 ;
b10 ,
b10 7
b10 :
b111101 6
b111101 %
b1 )
b1 0
b1 2
1/
#12200
0/
#12300
b11 +
b11 ;
b11 ,
b11 7
b11 :
b111110 6
b111110 %
b10 )
b10 0
b10 2
1/
#12400
0/
#12500
b100 +
b100 ;
b100 ,
b100 7
b100 :
b111111 6
b111111 %
b11 )
b11 0
b11 2
1/
#12600
0/
#12700
b101 +
b101 ;
b101 ,
b101 7
b101 :
b1000000 6
b1000000 %
b100 )
b100 0
b100 2
1/
#12800
0/
#12900
b110 +
b110 ;
b110 ,
b110 7
b110 :
b1000001 6
b1000001 %
b101 )
b101 0
b101 2
1/
#13000
0/
#13100
b111 +
b111 ;
b111 ,
b111 7
b111 :
b1000010 6
b1000010 %
b110 )
b110 0
b110 2
1/
#13200
0/
#13300
b1000 +
b1000 ;
b1000 ,
b1000 7
b1000 :
b1000011 6
b1000011 %
b111 )
b111 0
b111 2
1/
#13400
0/
#13500
b1001 +
b1001 ;
b1001 ,
b1001 7
b1001 :
b1000100 6
b1000100 %
b1000 )
b1000 0
b1000 2
1/
#13600
0/
#13700
b0 +
b0 ;
b1 *
b1 <
b1010 ,
b1010 7
b1010 :
b1000101 6
b1000101 %
b1001 )
b1001 0
b1001 2
1/
#13800
0/
#13900
b1 +
b1 ;
b1011 ,
b1011 7
b1011 :
b0 )
b0 0
b0 2
b1000110 6
b1000110 %
b111 &
b111 1
b111 3
1/
#14000
0/
#14100
b10 +
b10 ;
b1100 ,
b1100 7
b1100 :
b1000111 6
b1000111 %
b1 )
b1 0
b1 2
1/
#14200
0/
#14300
b11 +
b11 ;
b1101 ,
b1101 7
b1101 :
b1001000 6
b1001000 %
b10 )
b10 0
b10 2
1/
#14400
0/
#14500
b100 +
b100 ;
b1110 ,
b1110 7
b1110 :
b1001001 6
b1001001 %
b11 )
b11 0
b11 2
1/
#14600
0/
#14700
b101 +
b101 ;
b1111 ,
b1111 7
b1111 :
b1001010 6
b1001010 %
b100 )
b100 0
b100 2
1/
#14800
0/
#14900
b110 +
b110 ;
b10000 ,
b10000 7
b10000 :
b1001011 6
b1001011 %
b101 )
b101 0
b101 2
1/
#15000
0/
#15100
b111 +
b111 ;
b10001 ,
b10001 7
b10001 :
b1001100 6
b1001100 %
b110 )
b110 0
b110 2
1/
#15200
0/
#15300
b1000 +
b1000 ;
b10010 ,
b10010 7
b10010 :
b1001101 6
b1001101 %
b111 )
b111 0
b111 2
1/
#15400
0/
#15500
b1001 +
b1001 ;
b10011 ,
b10011 7
b10011 :
b1001110 6
b1001110 %
b1000 )
b1000 0
b1000 2
1/
#15600
0/
#15700
b0 +
b0 ;
b10 *
b10 <
b10100 ,
b10100 7
b10100 :
b1001111 6
b1001111 %
b1001 )
b1001 0
b1001 2
1/
#15800
0/
#15900
b1 +
b1 ;
b10101 ,
b10101 7
b10101 :
b0 )
b0 0
b0 2
b1010000 6
b1010000 %
b1000 &
b1000 1
b1000 3
1/
#16000
0/
#16100
b10 +
b10 ;
b10110 ,
b10110 7
b10110 :
b1010001 6
b1010001 %
b1 )
b1 0
b1 2
1/
#16200
0/
#16300
b11 +
b11 ;
b10111 ,
b10111 7
b10111 :
b1010010 6
b1010010 %
b10 )
b10 0
b10 2
1/
#16400
0/
#16500
b100 +
b100 ;
b11000 ,
b11000 7
b11000 :
b1010011 6
b1010011 %
b11 )
b11 0
b11 2
1/
#16600
0/
#16700
b101 +
b101 ;
b11001 ,
b11001 7
b11001 :
b1010100 6
b1010100 %
b100 )
b100 0
b100 2
1/
#16800
0/
#16900
b110 +
b110 ;
b11010 ,
b11010 7
b11010 :
b1010101 6
b1010101 %
b101 )
b101 0
b101 2
1/
#17000
0/
#17100
b111 +
b111 ;
b11011 ,
b11011 7
b11011 :
b1010110 6
b1010110 %
b110 )
b110 0
b110 2
1/
#17200
0/
#17300
b1000 +
b1000 ;
b11100 ,
b11100 7
b11100 :
b1010111 6
b1010111 %
b111 )
b111 0
b111 2
1/
#17400
0/
#17500
b1001 +
b1001 ;
b11101 ,
b11101 7
b11101 :
b1011000 6
b1011000 %
b1000 )
b1000 0
b1000 2
1/
#17600
0/
#17700
b0 +
b0 ;
b11 *
b11 <
b11110 ,
b11110 7
b11110 :
b1011001 6
b1011001 %
b1001 )
b1001 0
b1001 2
1/
#17800
0/
#17900
b1 +
b1 ;
b11111 ,
b11111 7
b11111 :
b0 )
b0 0
b0 2
b1011010 6
b1011010 %
b1001 &
b1001 1
b1001 3
1/
#18000
0/
#18100
b0 *
b0 <
b1 ,
b1 7
b1 :
b100 (
b100 8
b1011011 6
b1011011 %
b1 )
b1 0
b1 2
1/
#18200
0/
#18300
b10 +
b10 ;
b10 ,
b10 7
b10 :
b1011100 6
b1011100 %
b10 )
b10 0
b10 2
1/
#18400
0/
#18500
b11 +
b11 ;
b11 ,
b11 7
b11 :
b1011101 6
b1011101 %
b11 )
b11 0
b11 2
1/
#18600
0/
#18700
b100 +
b100 ;
b100 ,
b100 7
b100 :
b1011110 6
b1011110 %
b100 )
b100 0
b100 2
1/
#18800
0/
#18900
b101 +
b101 ;
b101 ,
b101 7
b101 :
b1011111 6
b1011111 %
b101 )
b101 0
b101 2
1/
#19000
0/
#19100
b110 +
b110 ;
b110 ,
b110 7
b110 :
b1100000 6
b1100000 %
b110 )
b110 0
b110 2
1/
#19200
0/
#19300
b111 +
b111 ;
b111 ,
b111 7
b111 :
b1100001 6
b1100001 %
b111 )
b111 0
b111 2
1/
#19400
0/
#19500
b1000 +
b1000 ;
b1000 ,
b1000 7
b1000 :
b1100010 6
b1100010 %
b1000 )
b1000 0
b1000 2
1/
#19600
0/
#19700
b1001 +
b1001 ;
b1001 ,
b1001 7
b1001 :
b1100011 6
b1100011 %
b1001 )
b1001 0
b1001 2
1/
#19800
0/
#19900
b1 +
b1 ;
b1 ,
b1 7
b1 :
b1 (
b1 8
b0 &
b0 1
b0 3
b1 6
b1 %
b1 )
b1 0
b1 2
1/
#20000
0/
#20100
b10 +
b10 ;
b10 ,
b10 7
b10 :
b10 6
b10 %
b10 )
b10 0
b10 2
1/
#20200
0/
#20300
b11 +
b11 ;
b11 ,
b11 7
b11 :
b11 6
b11 %
b11 )
b11 0
b11 2
1/
#20400
0/
#20500
b100 +
b100 ;
b100 ,
b100 7
b100 :
b100 6
b100 %
b100 )
b100 0
b100 2
1/
#20600
0/
#20700
b101 +
b101 ;
b101 ,
b101 7
b101 :
b101 6
b101 %
b101 )
b101 0
b101 2
1/
#20800
0/
#20900
b110 +
b110 ;
b110 ,
b110 7
b110 :
b110 6
b110 %
b110 )
b110 0
b110 2
1/
#21000
0/
#21100
b111 +
b111 ;
b111 ,
b111 7
b111 :
b111 6
b111 %
b111 )
b111 0
b111 2
1/
#21200
0/
#21300
b1000 +
b1000 ;
b1000 ,
b1000 7
b1000 :
b1000 6
b1000 %
b1000 )
b1000 0
b1000 2
1/
#21400
0/
#21500
b1001 +
b1001 ;
b1001 ,
b1001 7
b1001 :
b1001 6
b1001 %
b1001 )
b1001 0
b1001 2
1/
#21600
0/
#21700
b0 +
b0 ;
b1 *
b1 <
b1010 ,
b1010 7
b1010 :
b0 )
b0 0
b0 2
b1010 6
b1010 %
b1 &
b1 1
b1 3
1/
#21800
0/
#21900
b1 +
b1 ;
b1011 ,
b1011 7
b1011 :
b1011 6
b1011 %
b1 )
b1 0
b1 2
1/
#22000
0/
#22100
b10 +
b10 ;
b1100 ,
b1100 7
b1100 :
b1100 6
b1100 %
b10 )
b10 0
b10 2
1/
