Project2/Source/frequency.vh
`ifdef h2z
   
    divide_by = 5_000_000;
    
    
`else

    divide_by = 2_000_000;

    
`endif

Project2/Source/decoder.v
module decoder(
    input [3:0] MSB,birth,
    output reg [7:0] HEX
);

always @(birth)
begin
    case(birth)
        4'b0000: HEX = (MSB == 4'b0000)? 8'b1111_1111:8'b1100_0000;
        4'b0001: HEX = 8'b1111_1001;    //1
        4'b0010: HEX = 8'b1010_0100;    //2
        4'b0011: HEX = 8'b1011_0000;    //3
        4'b0100: HEX = 8'b1001_1001;    //4
        4'b0101: HEX = 8'b1001_0010;    //5 
        4'b0110: HEX = 8'b1000_0010;    //6
        4'b0111: HEX = 8'b1111_1000;    //7
        4'b1000: HEX = 8'b1000_0000;    //8
        4'b1001: HEX = 8'b1001_1000;    //9
       
        default HEX= 8'b1111_1111;
    endcase
    
end


endmodule

Project2/Source/DD_MSB_LSB.v
module DD_MSB_LSB(
input [4:0] DD,
output reg [3:0] DD_MSB,DD_LSB

);


always@(DD)
begin
    if (DD < 10) begin
        DD_MSB = 0;
        DD_LSB = DD;
    end

    else if (DD< 20)begin
        DD_MSB = 1;
        DD_LSB = DD-10 ;
    end
    else if (DD <30) begin
        DD_MSB = 2;
        DD_LSB = DD-20;

    end  
    else 
    begin
        DD_MSB = 3;
        DD_LSB = DD-30;
    end 
end



endmodule

Project2/Source/DDMM1.v
module DDMM1(
input wire  [3:0] MSB,LSB,
//input  clock, reset_n,
input [9:0] SW,
output reg[4:0] DD,
output reg[3:0] MM,MM_MSB

);
wire [7:0] binary_value;
assign binary_value = (MSB[3:0]*10)+({4'b0,LSB[3:0]});   // 4 bits to decimal



wire leap_year;
assign leap_year = SW[9];


always@(*)
begin
    
     if (binary_value <= 31) begin          // January
        MM <= 1;
        DD <= binary_value; // 
        MM_MSB = 0;
    end
    else if (binary_value <= 31+28+leap_year) begin  //Feb
        MM <= 2;
        DD <= binary_value - 31;
        MM_MSB = 0;
    end
    else if (binary_value <= 31+28+leap_year+31) begin // March
        MM <= 3;
        DD <= binary_value - 31-28-leap_year;
        MM_MSB = 0;
    end
    else  begin                                         // April
        MM <= 4;
        DD <= binary_value-31-28-leap_year-31;
        MM_MSB = 0;
    end
end



endmodule

Project2/Source/counterBCD.v
module counterBCD(
    input clock, reset_n,
    output reg [3:0] countLSB, countMSB
    //output wire [7:0] HEX5,HEX4
);


always @(posedge clock, negedge reset_n ) 
begin
    if (reset_n == 0)
        begin
            countLSB <= 1;             // Reset LEB = 1
            countMSB <= 0;             // Reset MSB = 0;
        end
    
    else if (countLSB != 9) 
        begin
            countLSB <= countLSB + 1;       //LSB counter
        end
    else if (countMSB == 9 && countLSB==9 )         // Roll over / same as reset 
        begin
            countLSB <= 1;
            countMSB <= 0;
        end
            
    else
        begin
            if(countLSB == 9)begin              //MSB counter
                    countMSB <= countMSB+1;
                end
            countLSB <=0;                       // When LSB count to 9, roll over
                
               
        end    
end
endmodule

HW10/Source/clock_divider.v
module clock_divider(
    input clock_in, reset_n,
    output reg clock_out
    //output [9:0] LEDR
);

reg [22:0] clock_divider;
//parameter divide_by = 5_000_000;
parameter divide_by = 0;

always@(posedge clock_in,negedge reset_n)
begin
    if(~reset_n)
        begin
            clock_out = 0;
            clock_divider = 0;
        end
     else
        begin
            if(clock_divider != divide_by-1)begin
               clock_divider <= clock_divider+1; 
            end
            else begin
                clock_divider <= 0;
                clock_out = ~clock_out;
            end    
        end   
end

endmodule

Project2/Source/Project2.v
//`include "frequency.vh"

module Project2(
    input ADC_CLK_10,
    input[1:0] KEY,
    input[9:0] SW,
    output [7:0] HEX5,HEX4,HEX3,HEX2,HEX1,HEX0,
    output wire[9:0] LEDR
);
wire clock2HZ,clock5HZ,clock;
wire reset_n ;
wire [3:0] MSB,LSB,MM,DD_MSB,DD_LSB,MM_MSB;
wire [4:0] DD;

assign LEDR[0] = KEY[1]? clock2HZ:clock5HZ;
assign clock = KEY[1]? clock2HZ:clock5HZ;
assign reset_n = KEY[0]? KEY[0]:KEY[0];


clock_divider  #(5_000_000) F2hz (.reset_n(reset_n),.clock_in(ADC_CLK_10),.clock_out(clock2HZ));

clock_divider #(2_000_000) F5hz (.reset_n(reset_n),.clock_in(ADC_CLK_10),.clock_out(clock5HZ));

counterBCD C1(.clock(clock),.reset_n(reset_n),.countMSB(MSB),.countLSB(LSB));
DDMM1 D1(.MSB(MSB),.LSB(LSB),.DD(DD),.MM(MM),.SW(SW),.MM_MSB(MM_MSB));

DD_MSB_LSB D2(.DD(DD),.DD_MSB(DD_MSB),.DD_LSB(DD_LSB));

decoder H5(.birth(MSB),.MSB(MSB),.HEX(HEX5));   //HEX5
decoder H4(.birth(LSB),.MSB(MSB),.HEX(HEX4));   //HEX4

decoder H3(.birth(MM_MSB),.MSB(MM_MSB),.HEX(HEX3));   //HEX3
decoder H2(.birth(MM),.MSB(MM_MSB),.HEX(HEX2));   //HEX2

decoder H1(.birth(DD_MSB),.MSB(DD_MSB),.HEX(HEX1));   //HEX1
decoder H0(.birth(DD_LSB),.MSB(DD_MSB),.HEX(HEX0));   //HEX0
endmodule

Project2/Source/tb_Project2.v
//`include "frequency.vh"
`timescale 1 ns / 100 ps
module tb_Project2();


reg [1:0]KEY;
reg [9:0] SW;
reg ADC_CLK_10;

wire [7:0] HEX5,HEX4,HEX3,HEX2,HEX1,HEX0;
wire [9:0] LEDR;

Project2 top (.ADC_CLK_10(ADC_CLK_10),.KEY(KEY),.SW(SW),.HEX5(HEX5),.HEX4(HEX4),.HEX3(HEX3),.HEX2(HEX2),.HEX1(HEX1),.HEX0(HEX0),.LEDR(LEDR));

always #10 ADC_CLK_10 = ~ADC_CLK_10;

initial
begin
    $dumpfile("tb_top.vcd");$dumpvars;
    ADC_CLK_10 = 0; SW[9]=0; KEY[0] = 0;KEY[1] =1;

    #100 KEY[0] = 1;
    #20000;
    #1000 SW[9] = 1;
    #3000;
    #100 $finish;
end


endmodule

Project2/TestbenchOutput/tb_top.vcd
$date
	Fri Oct 23 18:02:34 2020
$end
$version
	Icarus Verilog
$end
$timescale
	100ps
$end
$scope module tb_Project2 $end
$var wire 10 ! LEDR [9:0] $end
$var wire 8 " HEX5 [7:0] $end
$var wire 8 # HEX4 [7:0] $end
$var wire 8 $ HEX3 [7:0] $end
$var wire 8 % HEX2 [7:0] $end
$var wire 8 & HEX1 [7:0] $end
$var wire 8 ' HEX0 [7:0] $end
$var reg 1 ( ADC_CLK_10 $end
$var reg 2 ) KEY [1:0] $end
$var reg 10 * SW [9:0] $end
$scope module top $end
$var wire 1 ( ADC_CLK_10 $end
$var wire 2 + KEY [1:0] $end
$var wire 10 , SW [9:0] $end
$var wire 1 - reset_n $end
$var wire 1 . clock5HZ $end
$var wire 1 / clock2HZ $end
$var wire 1 0 clock $end
$var wire 4 1 MSB [3:0] $end
$var wire 4 2 MM_MSB [3:0] $end
$var wire 4 3 MM [3:0] $end
$var wire 4 4 LSB [3:0] $end
$var wire 10 5 LEDR [9:0] $end
$var wire 8 6 HEX5 [7:0] $end
$var wire 8 7 HEX4 [7:0] $end
$var wire 8 8 HEX3 [7:0] $end
$var wire 8 9 HEX2 [7:0] $end
$var wire 8 : HEX1 [7:0] $end
$var wire 8 ; HEX0 [7:0] $end
$var wire 4 < DD_MSB [3:0] $end
$var wire 4 = DD_LSB [3:0] $end
$var wire 5 > DD [4:0] $end
$scope module C1 $end
$var wire 1 0 clock $end
$var wire 1 - reset_n $end
$var reg 4 ? countLSB [3:0] $end
$var reg 4 @ countMSB [3:0] $end
$upscope $end
$scope module D1 $end
$var wire 4 A LSB [3:0] $end
$var wire 4 B MSB [3:0] $end
$var wire 10 C SW [9:0] $end
$var wire 1 D leap_year $end
$var wire 8 E binary_value [7:0] $end
$var reg 5 F DD [4:0] $end
$var reg 4 G MM [3:0] $end
$var reg 4 H MM_MSB [3:0] $end
$upscope $end
$scope module D2 $end
$var wire 5 I DD [4:0] $end
$var reg 4 J DD_LSB [3:0] $end
$var reg 4 K DD_MSB [3:0] $end
$upscope $end
$scope module F2hz $end
$var wire 1 ( clock_in $end
$var wire 1 - reset_n $end
$var reg 23 L clock_divider [22:0] $end
$var reg 1 / clock_out $end
$upscope $end
$scope module F5hz $end
$var wire 1 ( clock_in $end
$var wire 1 - reset_n $end
$var reg 23 M clock_divider [22:0] $end
$var reg 1 . clock_out $end
$upscope $end
$scope module H0 $end
$var wire 4 N MSB [3:0] $end
$var wire 4 O birth [3:0] $end
$var reg 8 P HEX [7:0] $end
$upscope $end
$scope module H1 $end
$var wire 4 Q MSB [3:0] $end
$var wire 4 R birth [3:0] $end
$var reg 8 S HEX [7:0] $end
$upscope $end
$scope module H2 $end
$var wire 4 T MSB [3:0] $end
$var wire 4 U birth [3:0] $end
$var reg 8 V HEX [7:0] $end
$upscope $end
$scope module H3 $end
$var wire 4 W MSB [3:0] $end
$var wire 4 X birth [3:0] $end
$var reg 8 Y HEX [7:0] $end
$upscope $end
$scope module H4 $end
$var wire 4 Z MSB [3:0] $end
$var wire 4 [ birth [3:0] $end
$var reg 8 \ HEX [7:0] $end
$upscope $end
$scope module H5 $end
$var wire 4 ] MSB [3:0] $end
$var wire 4 ^ birth [3:0] $end
$var reg 8 _ HEX [7:0] $end
$upscope $end
$upscope $end
$upscope $end
$enddefinitions $end
#0
$dumpvars
b11111111 _
b0 ^
b0 ]
b11111001 \
b1 [
b0 Z
b11111111 Y
b0 X
b0 W
b11111001 V
b1 U
b0 T
b11111111 S
b0 R
b0 Q
b11111001 P
b1 O
b0 N
b0 M
b0 L
b0 K
b1 J
b1 I
b0 H
b1 G
b1 F
b1 E
0D
b0xxxxxxxxx C
b0 B
b1 A
b0 @
b1 ?
b1 >
b1 =
b0 <
b11111001 ;
b11111111 :
b11111001 9
b11111111 8
b11111001 7
b11111111 6
bz0 5
b1 4
b1 3
b0 2
b0 1
00
0/
0.
0-
b0xxxxxxxxx ,
b10 +
b0xxxxxxxxx *
b10 )
0(
b11111001 '
b11111111 &
b11111001 %
b11111111 $
b11111001 #
b11111111 "
bz0 !
$end
#100
1(
#200
0(
#300
1(
#400
0(
#500
1(
#600
0(
#700
1(
#800
0(
#900
1(
#1000
1-
0(
b11 )
b11 +
#1100
b1 L
b1 M
1(
#1200
0(
#1300
b10 M
b10 L
1(
#1400
0(
#1500
b11 L
b11 M
1(
#1600
0(
#1700
b100 M
b100 L
1(
#1800
0(
#1900
b101 L
b101 M
1(
#2000
0(
#2100
b110 M
b110 L
1(
#2200
0(
#2300
b111 L
b111 M
1(
#2400
0(
#2500
b1000 M
b1000 L
1(
#2600
0(
#2700
b1001 L
b1001 M
1(
#2800
0(
#2900
b1010 M
b1010 L
1(
#3000
0(
#3100
b1011 L
b1011 M
1(
#3200
0(
#3300
b1100 M
b1100 L
1(
#3400
0(
#3500
b1101 L
b1101 M
1(
#3600
0(
#3700
b1110 M
b1110 L
1(
#3800
0(
#3900
b1111 L
b1111 M
1(
#4000
0(
#4100
b10000 M
b10000 L
1(
#4200
0(
#4300
b10001 L
b10001 M
1(
#4400
0(
#4500
b10010 M
b10010 L
1(
#4600
0(
#4700
b10011 L
b10011 M
1(
#4800
0(
#4900
b10100 M
b10100 L
1(
#5000
0(
#5100
b10101 L
b10101 M
1(
#5200
0(
#5300
b10110 M
b10110 L
1(
#5400
0(
#5500
b10111 L
b10111 M
1(
#5600
0(
#5700
b11000 M
b11000 L
1(
#5800
0(
#5900
b11001 L
b11001 M
1(
#6000
0(
#6100
b11010 M
b11010 L
1(
#6200
0(
#6300
b11011 L
b11011 M
1(
#6400
0(
#6500
b11100 M
b11100 L
1(
#6600
0(
#6700
b11101 L
b11101 M
1(
#6800
0(
#6900
b11110 M
b11110 L
1(
#7000
0(
#7100
b11111 L
b11111 M
1(
#7200
0(
#7300
b100000 M
b100000 L
1(
#7400
0(
#7500
b100001 L
b100001 M
1(
#7600
0(
#7700
b100010 M
b100010 L
1(
#7800
0(
#7900
b100011 L
b100011 M
1(
#8000
0(
#8100
b100100 M
b100100 L
1(
#8200
0(
#8300
b100101 L
b100101 M
1(
#8400
0(
#8500
b100110 M
b100110 L
1(
#8600
0(
#8700
b100111 L
b100111 M
1(
#8800
0(
#8900
b101000 M
b101000 L
1(
#9000
0(
#9100
b101001 L
b101001 M
1(
#9200
0(
#9300
b101010 M
b101010 L
1(
#9400
0(
#9500
b101011 L
b101011 M
1(
#9600
0(
#9700
b101100 M
b101100 L
1(
#9800
0(
#9900
b101101 L
b101101 M
1(
#10000
0(
#10100
b101110 M
b101110 L
1(
#10200
0(
#10300
b101111 L
b101111 M
1(
#10400
0(
#10500
b110000 M
b110000 L
1(
#10600
0(
#10700
b110001 L
b110001 M
1(
#10800
0(
#10900
b110010 M
b110010 L
1(
#11000
0(
#11100
b110011 L
b110011 M
1(
#11200
0(
#11300
b110100 M
b110100 L
1(
#11400
0(
#11500
b110101 L
b110101 M
1(
#11600
0(
#11700
b110110 M
b110110 L
1(
#11800
0(
#11900
b110111 L
b110111 M
1(
#12000
0(
#12100
b111000 M
b111000 L
1(
#12200
0(
#12300
b111001 L
b111001 M
1(
#12400
0(
#12500
b111010 M
b111010 L
1(
#12600
0(
#12700
b111011 L
b111011 M
1(
#12800
0(
#12900
b111100 M
b111100 L
1(
#13000
0(
#13100
b111101 L
b111101 M
1(
#13200
0(
#13300
b111110 M
b111110 L
1(
#13400
0(
#13500
b111111 L
b111111 M
1(
#13600
0(
#13700
b1000000 M
b1000000 L
1(
#13800
0(
#13900
b1000001 L
b1000001 M
1(
#14000
0(
#14100
b1000010 M
b1000010 L
1(
#14200
0(
#14300
b1000011 L
b1000011 M
1(
#14400
0(
#14500
b1000100 M
b1000100 L
1(
#14600
0(
#14700
b1000101 L
b1000101 M
1(
#14800
0(
#14900
b1000110 M
b1000110 L
1(
#15000
0(
#15100
b1000111 L
b1000111 M
1(
#15200
0(
#15300
b1001000 M
b1001000 L
1(
#15400
0(
#15500
b1001001 L
b1001001 M
1(
#15600
0(
#15700
b1001010 M
b1001010 L
1(
#15800
0(
#15900
b1001011 L
b1001011 M
1(
#16000
0(
#16100
b1001100 M
b1001100 L
1(
#16200
0(
#16300
b1001101 L
b1001101 M
1(
#16400
0(
#16500
b1001110 M
b1001110 L
1(
#16600
0(
#16700
b1001111 L
b1001111 M
1(
#16800
0(
#16900
b1010000 M
b1010000 L
1(
#17000
0(
#17100
b1010001 L
b1010001 M
1(
#17200
0(
#17300
b1010010 M
b1010010 L
1(
#17400
0(
#17500
b1010011 L
b1010011 M
1(
#17600
0(
#17700
b1010100 M
b1010100 L
1(
#17800
0(
#17900
b1010101 L
b1010101 M
1(
#18000
0(
#18100
b1010110 M
b1010110 L
1(
#18200
0(
#18300
b1010111 L
b1010111 M
1(
#18400
0(
#18500
b1011000 M
b1011000 L
1(
#18600
0(
#18700
b1011001 L
b1011001 M
1(
#18800
0(
#18900
b1011010 M
b1011010 L
1(
#19000
0(
#19100
b1011011 L
b1011011 M
1(
#19200
0(
#19300
b1011100 M
b1011100 L
1(
#19400
0(
#19500
b1011101 L
b1011101 M
1(
#19600
0(
#19700
b1011110 M
b1011110 L
1(
#19800
0(
#19900
b1011111 L
b1011111 M
1(
#20000
0(
#20100
b1100000 M
b1100000 L
1(
#20200
0(
#20300
b1100001 L
b1100001 M
1(
#20400
0(
#20500
b1100010 M
b1100010 L
1(
#20600
0(
#20700
b1100011 L
b1100011 M
1(
#20800
0(
#20900
b1100100 M
b1100100 L
1(
#21000
0(
#21100
b1100101 L
b1100101 M
1(
#21200
0(
#21300
b1100110 M
b1100110 L
1(
#21400
0(
#21500
b1100111 L
b1100111 M
1(
#21600
0(
#21700
b1101000 M
b1101000 L
1(
#21800
0(
#21900
b1101001 L
b1101001 M
1(
#22000
0(
#22100
b1101010 M
b1101010 L
1(
#22200
0(
#22300
b1101011 L
b1101011 M
1(
#22400
0(
#22500
b1101100 M
b1101100 L
1(
#22600
0(
#22700
b1101101 L
b1101101 M
1(
#22800
0(
#22900
b1101110 M
b1101110 L
1(
#23000
0(
#23100
b1101111 L
b1101111 M
1(
#23200
0(
#23300
b1110000 M
b1110000 L
1(
#23400
0(
#23500
b1110001 L
b1110001 M
1(
#23600
0(
#23700
b1110010 M
b1110010 L
1(
#23800
0(
#23900
b1110011 L
b1110011 M
1(
#24000
0(
#24100
b1110100 M
b1110100 L
1(
#24200
0(
#24300
b1110101 L
b1110101 M
1(
#24400
0(
#24500
b1110110 M
b1110110 L
1(
#24600
0(
#24700
b1110111 L
b1110111 M
1(
#24800
0(
#24900
b1111000 M
b1111000 L
1(
#25000
0(
#25100
b1111001 L
b1111001 M
1(
#25200
0(
#25300
b1111010 M
b1111010 L
1(
#25400
0(
#25500
b1111011 L
b1111011 M
1(
#25600
0(
#25700
b1111100 M
b1111100 L
1(
#25800
0(
#25900
b1111101 L
b1111101 M
1(
#26000
0(
#26100
b1111110 M
b1111110 L
1(
#26200
0(
#26300
b1111111 L
b1111111 M
1(
#26400
0(
#26500
b10000000 M
b10000000 L
1(
#26600
0(
#26700
b10000001 L
b10000001 M
1(
#26800
0(
#26900
b10000010 M
b10000010 L
1(
#27000
0(
#27100
b10000011 L
b10000011 M
1(
#27200
0(
#27300
b10000100 M
b10000100 L
1(
#27400
0(
#27500
b10000101 L
b10000101 M
1(
#27600
0(
#27700
b10000110 M
b10000110 L
1(
#27800
0(
#27900
b10000111 L
b10000111 M
1(
#28000
0(
#28100
b10001000 M
b10001000 L
1(
#28200
0(
#28300
b10001001 L
b10001001 M
1(
#28400
0(
#28500
b10001010 M
b10001010 L
1(
#28600
0(
#28700
b10001011 L
b10001011 M
1(
#28800
0(
#28900
b10001100 M
b10001100 L
1(
#29000
0(
#29100
b10001101 L
b10001101 M
1(
#29200
0(
#29300
b10001110 M
b10001110 L
1(
#29400
0(
#29500
b10001111 L
b10001111 M
1(
#29600
0(
#29700
b10010000 M
b10010000 L
1(
#29800
0(
#29900
b10010001 L
b10010001 M
1(
#30000
0(
#30100
b10010010 M
b10010010 L
1(
#30200
0(
#30300
b10010011 L
b10010011 M
1(
#30400
0(
#30500
b10010100 M
b10010100 L
1(
#30600
0(
#30700
b10010101 L
b10010101 M
1(
#30800
0(
#30900
b10010110 M
b10010110 L
1(
#31000
0(
#31100
b10010111 L
b10010111 M
1(
#31200
0(
#31300
b10011000 M
b10011000 L
1(
#31400
0(
#31500
b10011001 L
b10011001 M
1(
#31600
0(
#31700
b10011010 M
b10011010 L
1(
#31800
0(
#31900
b10011011 L
b10011011 M
1(
#32000
0(
#32100
b10011100 M
b10011100 L
1(
#32200
0(
#32300
b10011101 L
b10011101 M
1(
#32400
0(
#32500
b10011110 M
b10011110 L
1(
#32600
0(
#32700
b10011111 L
b10011111 M
1(
#32800
0(
#32900
b10100000 M
b10100000 L
1(
#33000
0(
#33100
b10100001 L
b10100001 M
1(
#33200
0(
#33300
b10100010 M
b10100010 L
1(
#33400
0(
#33500
b10100011 L
b10100011 M
1(
#33600
0(
#33700
b10100100 M
b10100100 L
1(
#33800
0(
#33900
b10100101 L
b10100101 M
1(
#34000
0(
#34100
b10100110 M
b10100110 L
1(
#34200
0(
#34300
b10100111 L
b10100111 M
1(
#34400
0(
#34500
b10101000 M
b10101000 L
1(
#34600
0(
#34700
b10101001 L
b10101001 M
1(
#34800
0(
#34900
b10101010 M
b10101010 L
1(
#35000
0(
#35100
b10101011 L
b10101011 M
1(
#35200
0(
#35300
b10101100 M
b10101100 L
1(
#35400
0(
#35500
b10101101 L
b10101101 M
1(
#35600
0(
#35700
b10101110 M
b10101110 L
1(
#35800
0(
#35900
b10101111 L
b10101111 M
1(
#36000
0(
#36100
b10110000 M
b10110000 L
1(
#36200
0(
#36300
b10110001 L
b10110001 M
1(
#36400
0(
#36500
b10110010 M
b10110010 L
1(
#36600
0(
#36700
b10110011 L
b10110011 M
1(
#36800
0(
#36900
b10110100 M
b10110100 L
1(
#37000
0(
#37100
b10110101 L
b10110101 M
1(
#37200
0(
#37300
b10110110 M
b10110110 L
1(
#37400
0(
#37500
b10110111 L
b10110111 M
1(
#37600
0(
#37700
b10111000 M
b10111000 L
1(
#37800
0(
#37900
b10111001 L
b10111001 M
1(
#38000
0(
#38100
b10111010 M
b10111010 L
1(
#38200
0(
#38300
b10111011 L
b10111011 M
1(
#38400
0(
#38500
b10111100 M
b10111100 L
1(
#38600
0(
#38700
b10111101 L
b10111101 M
1(
#38800
0(
#38900
b10111110 M
b10111110 L
1(
#39000
0(
#39100
b10111111 L
b10111111 M
1(
#39200
0(
#39300
b11000000 M
b11000000 L
1(
#39400
0(
#39500
b11000001 L
b11000001 M
1(
#39600
0(
#39700
b11000010 M
b11000010 L
1(
#39800
0(
#39900
b11000011 L
b11000011 M
1(
#40000
0(
#40100
b11000100 M
b11000100 L
1(
#40200
0(
#40300
b11000101 L
b11000101 M
1(
#40400
0(
#40500
b11000110 M
b11000110 L
1(
#40600
0(
#40700
b11000111 L
b11000111 M
1(
#40800
0(
#40900
b0 M
b11001000 L
1.
1(
#41000
0(
#41100
b11001001 L
b1 M
1(
#41200
0(
#41300
b10 M
b11001010 L
1(
#41400
0(
#41500
b11001011 L
b11 M
1(
#41600
0(
#41700
b100 M
b11001100 L
1(
#41800
0(
#41900
b11001101 L
b101 M
1(
#42000
0(
#42100
b110 M
b11001110 L
1(
#42200
0(
#42300
b11001111 L
b111 M
1(
#42400
0(
#42500
b1000 M
b11010000 L
1(
#42600
0(
#42700
b11010001 L
b1001 M
1(
#42800
0(
#42900
b1010 M
b11010010 L
1(
#43000
0(
#43100
b11010011 L
b1011 M
1(
#43200
0(
#43300
b1100 M
b11010100 L
1(
#43400
0(
#43500
b11010101 L
b1101 M
1(
#43600
0(
#43700
b1110 M
b11010110 L
1(
#43800
0(
#43900
b11010111 L
b1111 M
1(
#44000
0(
#44100
b10000 M
b11011000 L
1(
#44200
0(
#44300
b11011001 L
b10001 M
1(
#44400
0(
#44500
b10010 M
b11011010 L
1(
#44600
0(
#44700
b11011011 L
b10011 M
1(
#44800
0(
#44900
b10100 M
b11011100 L
1(
#45000
0(
#45100
b11011101 L
b10101 M
1(
#45200
0(
#45300
b10110 M
b11011110 L
1(
#45400
0(
#45500
b11011111 L
b10111 M
1(
#45600
0(
#45700
b11000 M
b11100000 L
1(
#45800
0(
#45900
b11100001 L
b11001 M
1(
#46000
0(
#46100
b11010 M
b11100010 L
1(
#46200
0(
#46300
b11100011 L
b11011 M
1(
#46400
0(
#46500
b11100 M
b11100100 L
1(
#46600
0(
#46700
b11100101 L
b11101 M
1(
#46800
0(
#46900
b11110 M
b11100110 L
1(
#47000
0(
#47100
b11100111 L
b11111 M
1(
#47200
0(
#47300
b100000 M
b11101000 L
1(
#47400
0(
#47500
b11101001 L
b100001 M
1(
#47600
0(
#47700
b100010 M
b11101010 L
1(
#47800
0(
#47900
b11101011 L
b100011 M
1(
#48000
0(
#48100
b100100 M
b11101100 L
1(
#48200
0(
#48300
b11101101 L
b100101 M
1(
#48400
0(
#48500
b100110 M
b11101110 L
1(
#48600
0(
#48700
b11101111 L
b100111 M
1(
#48800
0(
#48900
b101000 M
b11110000 L
1(
#49000
0(
#49100
b11110001 L
b101001 M
1(
#49200
0(
#49300
b101010 M
b11110010 L
1(
#49400
0(
#49500
b11110011 L
b101011 M
1(
#49600
0(
#49700
b101100 M
b11110100 L
1(
#49800
0(
#49900
b11110101 L
b101101 M
1(
#50000
0(
#50100
b101110 M
b11110110 L
1(
#50200
0(
#50300
b11110111 L
b101111 M
1(
#50400
0(
#50500
b110000 M
b11111000 L
1(
#50600
0(
#50700
b11111001 L
b110001 M
1(
#50800
0(
#50900
b110010 M
b11111010 L
1(
#51000
0(
#51100
b11111011 L
b110011 M
1(
#51200
0(
#51300
b110100 M
b11111100 L
1(
#51400
0(
#51500
b11111101 L
b110101 M
1(
#51600
0(
#51700
b110110 M
b11111110 L
1(
#51800
0(
#51900
b11111111 L
b110111 M
1(
#52000
0(
#52100
b111000 M
b100000000 L
1(
#52200
0(
#52300
b100000001 L
b111001 M
1(
#52400
0(
#52500
b111010 M
b100000010 L
1(
#52600
0(
#52700
b100000011 L
b111011 M
1(
#52800
0(
#52900
b111100 M
b100000100 L
1(
#53000
0(
#53100
b100000101 L
b111101 M
1(
#53200
0(
#53300
b111110 M
b100000110 L
1(
#53400
0(
#53500
b100000111 L
b111111 M
1(
#53600
0(
#53700
b1000000 M
b100001000 L
1(
#53800
0(
#53900
b100001001 L
b1000001 M
1(
#54000
0(
#54100
b1000010 M
b100001010 L
1(
#54200
0(
#54300
b100001011 L
b1000011 M
1(
#54400
0(
#54500
b1000100 M
b100001100 L
1(
#54600
0(
#54700
b100001101 L
b1000101 M
1(
#54800
0(
#54900
b1000110 M
b100001110 L
1(
#55000
0(
#55100
b100001111 L
b1000111 M
1(
#55200
0(
#55300
b1001000 M
b100010000 L
1(
#55400
0(
#55500
b100010001 L
b1001001 M
1(
#55600
0(
#55700
b1001010 M
b100010010 L
1(
#55800
0(
#55900
b100010011 L
b1001011 M
1(
#56000
0(
#56100
b1001100 M
b100010100 L
1(
#56200
0(
#56300
b100010101 L
b1001101 M
1(
#56400
0(
#56500
b1001110 M
b100010110 L
1(
#56600
0(
#56700
b100010111 L
b1001111 M
1(
#56800
0(
#56900
b1010000 M
b100011000 L
1(
#57000
0(
#57100
b100011001 L
b1010001 M
1(
#57200
0(
#57300
b1010010 M
b100011010 L
1(
#57400
0(
#57500
b100011011 L
b1010011 M
1(
#57600
0(
#57700
b1010100 M
b100011100 L
1(
#57800
0(
#57900
b100011101 L
b1010101 M
1(
#58000
0(
#58100
b1010110 M
b100011110 L
1(
#58200
0(
#58300
b100011111 L
b1010111 M
1(
#58400
0(
#58500
b1011000 M
b100100000 L
1(
#58600
0(
#58700
b100100001 L
b1011001 M
1(
#58800
0(
#58900
b1011010 M
b100100010 L
1(
#59000
0(
#59100
b100100011 L
b1011011 M
1(
#59200
0(
#59300
b1011100 M
b100100100 L
1(
#59400
0(
#59500
b100100101 L
b1011101 M
1(
#59600
0(
#59700
b1011110 M
b100100110 L
1(
#59800
0(
#59900
b100100111 L
b1011111 M
1(
#60000
0(
#60100
b1100000 M
b100101000 L
1(
#60200
0(
#60300
b100101001 L
b1100001 M
1(
#60400
0(
#60500
b1100010 M
b100101010 L
1(
#60600
0(
#60700
b100101011 L
b1100011 M
1(
#60800
0(
#60900
b1100100 M
b100101100 L
1(
#61000
0(
#61100
b100101101 L
b1100101 M
1(
#61200
0(
#61300
b1100110 M
b100101110 L
1(
#61400
0(
#61500
b100101111 L
b1100111 M
1(
#61600
0(
#61700
b1101000 M
b100110000 L
1(
#61800
0(
#61900
b100110001 L
b1101001 M
1(
#62000
0(
#62100
b1101010 M
b100110010 L
1(
#62200
0(
#62300
b100110011 L
b1101011 M
1(
#62400
0(
#62500
b1101100 M
b100110100 L
1(
#62600
0(
#62700
b100110101 L
b1101101 M
1(
#62800
0(
#62900
b1101110 M
b100110110 L
1(
#63000
0(
#63100
b100110111 L
b1101111 M
1(
#63200
0(
#63300
b1110000 M
b100111000 L
1(
#63400
0(
#63500
b100111001 L
b1110001 M
1(
#63600
0(
#63700
b1110010 M
b100111010 L
1(
#63800
0(
#63900
b100111011 L
b1110011 M
1(
#64000
0(
#64100
b1110100 M
b100111100 L
1(
#64200
0(
#64300
b100111101 L
b1110101 M
1(
#64400
0(
#64500
b1110110 M
b100111110 L
1(
#64600
0(
#64700
b100111111 L
b1110111 M
1(
#64800
0(
#64900
b1111000 M
b101000000 L
1(
#65000
0(
#65100
b101000001 L
b1111001 M
1(
#65200
0(
#65300
b1111010 M
b101000010 L
1(
#65400
0(
#65500
b101000011 L
b1111011 M
1(
#65600
0(
#65700
b1111100 M
b101000100 L
1(
#65800
0(
#65900
b101000101 L
b1111101 M
1(
#66000
0(
#66100
b1111110 M
b101000110 L
1(
#66200
0(
#66300
b101000111 L
b1111111 M
1(
#66400
0(
#66500
b10000000 M
b101001000 L
1(
#66600
0(
#66700
b101001001 L
b10000001 M
1(
#66800
0(
#66900
b10000010 M
b101001010 L
1(
#67000
0(
#67100
b101001011 L
b10000011 M
1(
#67200
0(
#67300
b10000100 M
b101001100 L
1(
#67400
0(
#67500
b101001101 L
b10000101 M
1(
#67600
0(
#67700
b10000110 M
b101001110 L
1(
#67800
0(
#67900
b101001111 L
b10000111 M
1(
#68000
0(
#68100
b10001000 M
b101010000 L
1(
#68200
0(
#68300
b101010001 L
b10001001 M
1(
#68400
0(
#68500
b10001010 M
b101010010 L
1(
#68600
0(
#68700
b101010011 L
b10001011 M
1(
#68800
0(
#68900
b10001100 M
b101010100 L
1(
#69000
0(
#69100
b101010101 L
b10001101 M
1(
#69200
0(
#69300
b10001110 M
b101010110 L
1(
#69400
0(
#69500
b101010111 L
b10001111 M
1(
#69600
0(
#69700
b10010000 M
b101011000 L
1(
#69800
0(
#69900
b101011001 L
b10010001 M
1(
#70000
0(
#70100
b10010010 M
b101011010 L
1(
#70200
0(
#70300
b101011011 L
b10010011 M
1(
#70400
0(
#70500
b10010100 M
b101011100 L
1(
#70600
0(
#70700
b101011101 L
b10010101 M
1(
#70800
0(
#70900
b10010110 M
b101011110 L
1(
#71000
0(
#71100
b101011111 L
b10010111 M
1(
#71200
0(
#71300
b10011000 M
b101100000 L
1(
#71400
0(
#71500
b101100001 L
b10011001 M
1(
#71600
0(
#71700
b10011010 M
b101100010 L
1(
#71800
0(
#71900
b101100011 L
b10011011 M
1(
#72000
0(
#72100
b10011100 M
b101100100 L
1(
#72200
0(
#72300
b101100101 L
b10011101 M
1(
#72400
0(
#72500
b10011110 M
b101100110 L
1(
#72600
0(
#72700
b101100111 L
b10011111 M
1(
#72800
0(
