Homework3/HW9.v
module HW9(
    input clock_in,reset_n,
    output reg clock_out
);
reg [22:0] clock_divider ;
parameter divide_by = 3;
always@(posedge clock_in,negedge reset_n)
begin
    if(~reset_n)
        begin
            clock_out = 0;
            clock_divider = 0;
        end
     else
        begin
            if(clock_divider != divide_by-1)begin
               clock_divider <= clock_divider+1; 
            end
            else begin
                clock_divider <= 0;
                clock_out = ~clock_out;
            end    
        end   
end
always@(negedge clock_in,negedge reset_n)
begin
    if(~reset_n)
        begin
            clock_out = 0;
            clock_divider = 0;
        end
     else
        begin
            if(clock_divider != divide_by-1)begin
               clock_divider <= clock_divider+1; 
               
            end
            /*else if (clock_divider == 1) begin
                clock_out <= clock_out;
            end*/
            else  begin
                clock_divider <= 0;
                clock_out = ~clock_out;
            end    
        end   
end

endmodule

Homework3/tb_HW9.v
`timescale 1 ns /  100 ps
module tb_HW9();



reg reset_n;

reg clock = 0;
HW9 HW9 (.clock_in(clock),.reset_n(reset_n),.clock_out(clock_out));

always  #10 clock =~clock;
initial 
begin
    $dumpfile("HW9.vcd"); $dumpvars;
    clock = 0; reset_n = 0;
     
    #10 reset_n = 1;
    
    #3000;
    #100 $finish;

end

endmodule

Homework3/HW9.vcd
$date
	Wed Oct 28 09:26:12 2020
$end
$version
	Icarus Verilog
$end
$timescale
	100ps
$end
$scope module tb_HW9 $end
$var wire 1 ! clock_out $end
$var reg 1 " clock $end
$var reg 1 # reset_n $end
$scope module HW9 $end
$var wire 1 " clock_in $end
$var wire 1 # reset_n $end
$var reg 23 $ clock_divider [22:0] $end
$var reg 1 ! clock_out $end
$upscope $end
$upscope $end
$enddefinitions $end
#0
$dumpvars
b0 $
0#
0"
0!
$end
#100
b1 $
1#
1"
#200
b10 $
0"
#300
b0 $
1!
1"
#400
b1 $
0"
#500
b10 $
1"
#600
b0 $
0!
0"
#700
b1 $
1"
#800
b10 $
0"
#900
b0 $
1!
1"
#1000
b1 $
0"
#1100
b10 $
1"
#1200
b0 $
0!
0"
#1300
b1 $
1"
#1400
b10 $
0"
#1500
b0 $
1!
1"
#1600
b1 $
0"
#1700
b10 $
1"
#1800
b0 $
0!
0"
#1900
b1 $
1"
#2000
b10 $
0"
#2100
b0 $
1!
1"
#2200
b1 $
0"
#2300
b10 $
1"
#2400
b0 $
0!
0"
#2500
b1 $
1"
#2600
b10 $
0"
#2700
b0 $
1!
1"
#2800
b1 $
0"
#2900
b10 $
1"
#3000
b0 $
0!
0"
#3100
b1 $
1"
#3200
b10 $
0"
#3300
b0 $
1!
1"
#3400
b1 $
0"
#3500
b10 $
1"
#3600
b0 $
0!
0"
#3700
b1 $
1"
#3800
b10 $
0"
#3900
b0 $
1!
1"
#4000
b1 $
0"
#4100
b10 $
1"
#4200
b0 $
0!
0"
#4300
b1 $
1"
#4400
b10 $
0"
#4500
b0 $
1!
1"
#4600
b1 $
0"
#4700
b10 $
1"
#4800
b0 $
0!
0"
#4900
b1 $
1"
#5000
b10 $
0"
#5100
b0 $
1!
1"
#5200
b1 $
0"
#5300
b10 $
1"
#5400
b0 $
0!
0"
#5500
b1 $
1"
#5600
b10 $
0"
#5700
b0 $
1!
1"
#5800
b1 $
0"
#5900
b10 $
1"
#6000
b0 $
0!
0"
#6100
b1 $
1"
#6200
b10 $
0"
#6300
b0 $
1!
1"
#6400
b1 $
0"
#6500
b10 $
1"
#6600
b0 $
0!
0"
#6700
b1 $
1"
#6800
b10 $
0"
#6900
b0 $
1!
1"
#7000
b1 $
0"
#7100
b10 $
1"
#7200
b0 $
0!
0"
#7300
b1 $
1"
#7400
b10 $
0"
#7500
b0 $
1!
1"
#7600
b1 $
0"
#7700
b10 $
1"
#7800
b0 $
0!
0"
#7900
b1 $
1"
#8000
b10 $
0"
#8100
b0 $
1!
1"
#8200
b1 $
0"
#8300
b10 $
1"
#8400
b0 $
0!
0"
#8500
b1 $
1"
#8600
b10 $
0"
#8700
b0 $
1!
1"
#8800
b1 $
0"
#8900
b10 $
1"
#9000
b0 $
0!
0"
#9100
b1 $
1"
#9200
b10 $
0"
#9300
b0 $
1!
1"
#9400
b1 $
0"
#9500
b10 $
1"
#9600
b0 $
0!
0"
#9700
b1 $
1"
#9800
b10 $
0"
#9900
b0 $
1!
1"
#10000
b1 $
0"
#10100
b10 $
1"
#10200
b0 $
0!
0"
#10300
b1 $
1"
#10400
b10 $
0"
#10500
b0 $
1!
1"
#10600
b1 $
0"
#10700
b10 $
1"
#10800
b0 $
0!
0"
#10900
b1 $
1"
#11000
b10 $
0"
#11100
b0 $
1!
1"
#11200
b1 $
0"
#11300
b10 $
1"
#11400
b0 $
0!
0"
#11500
b1 $
1"
#11600
b10 $
0"
#11700
b0 $
1!
1"
#11800
b1 $
0"
#11900
b10 $
1"
#12000
b0 $
0!
0"
#12100
b1 $
1"
#12200
b10 $
0"
#12300
b0 $
1!
1"
#12400
b1 $
0"
#12500
b10 $
1"
#12600
b0 $
0!
0"
#12700
b1 $
1"
#12800
b10 $
0"
#12900
b0 $
1!
1"
#13000
b1 $
0"
#13100
b10 $
1"
#13200
b0 $
0!
0"
#13300
b1 $
1"
#13400
b10 $
0"
#13500
b0 $
1!
1"
#13600
b1 $
0"
#13700
b10 $
1"
#13800
b0 $
0!
0"
#13900
b1 $
1"
#14000
b10 $
0"
#14100
b0 $
1!
1"
#14200
b1 $
0"
#14300
b10 $
1"
#14400
b0 $
0!
0"
#14500
b1 $
1"
#14600
b10 $
0"
#14700
b0 $
1!
1"
#14800
b1 $
0"
#14900
b10 $
1"
#15000
b0 $
0!
0"
#15100
b1 $
1"
#15200
b10 $
0"
#15300
b0 $
1!
1"
#15400
b1 $
0"
#15500
b10 $
1"
#15600
b0 $
0!
0"
#15700
b1 $
1"
#15800
b10 $
0"
#15900
b0 $
1!
1"
#16000
b1 $
0"
#16100
b10 $
1"
#16200
b0 $
0!
0"
#16300
b1 $
1"
#16400
b10 $
0"
#16500
b0 $
1!
1"
#16600
b1 $
0"
#16700
b10 $
1"
#16800
b0 $
0!
0"
#16900
b1 $
1"
#17000
b10 $
0"
#17100
b0 $
1!
1"
#17200
b1 $
0"
#17300
b10 $
1"
#17400
b0 $
0!
0"
#17500
b1 $
1"
#17600
b10 $
0"
#17700
b0 $
1!
1"
#17800
b1 $
0"
#17900
b10 $
1"
#18000
b0 $
0!
0"
#18100
b1 $
1"
#18200
b10 $
0"
#18300
b0 $
1!
1"
#18400
b1 $
0"
#18500
b10 $
1"
#18600
b0 $
0!
0"
#18700
b1 $
1"
#18800
b10 $
0"
#18900
b0 $
1!
1"
#19000
b1 $
0"
#19100
b10 $
1"
#19200
b0 $
0!
0"
#19300
b1 $
1"
#19400
b10 $
0"
#19500
b0 $
1!
1"
#19600
b1 $
0"
#19700
b10 $
1"
#19800
b0 $
0!
0"
#19900
b1 $
1"
#20000
b10 $
0"
#20100
b0 $
1!
1"
#20200
b1 $
0"
#20300
b10 $
1"
#20400
b0 $
0!
0"
#20500
b1 $
1"
#20600
b10 $
0"
#20700
b0 $
1!
1"
#20800
b1 $
0"
#20900
b10 $
1"
#21000
b0 $
0!
0"
#21100
b1 $
1"
#21200
b10 $
0"
#21300
b0 $
1!
1"
#21400
b1 $
0"
#21500
b10 $
1"
#21600
b0 $
0!
0"
#21700
b1 $
1"
#21800
b10 $
0"
#21900
b0 $
1!
1"
#22000
b1 $
0"
#22100
b10 $
1"
#22200
b0 $
0!
0"
#22300
b1 $
1"
#22400
b10 $
0"
#22500
b0 $
1!
1"
#22600
b1 $
0"
#22700
b10 $
1"
#22800
b0 $
0!
0"
#22900
b1 $
1"
#23000
b10 $
0"
#23100
b0 $
1!
1"
#23200
b1 $
0"
#23300
b10 $
1"
#23400
b0 $
0!
0"
#23500
b1 $
1"
#23600
b10 $
0"
#23700
b0 $
1!
1"
#23800
b1 $
0"
#23900
b10 $
1"
#24000
b0 $
0!
0"
#24100
b1 $
1"
#24200
b10 $
0"
#24300
b0 $
1!
1"
#24400
b1 $
0"
#24500
b10 $
1"
#24600
b0 $
0!
0"
#24700
b1 $
1"
#24800
b10 $
0"
#24900
b0 $
1!
1"
#25000
b1 $
0"
#25100
b10 $
1"
#25200
b0 $
0!
0"
#25300
b1 $
1"
#25400
b10 $
0"
#25500
b0 $
1!
1"
#25600
b1 $
0"
#25700
b10 $
1"
#25800
b0 $
0!
0"
#25900
b1 $
1"
#26000
b10 $
0"
#26100
b0 $
1!
1"
#26200
b1 $
0"
#26300
b10 $
1"
#26400
b0 $
0!
0"
#26500
b1 $
1"
#26600
b10 $
0"
#26700
b0 $
1!
1"
#26800
b1 $
0"
#26900
b10 $
1"
#27000
b0 $
0!
0"
#27100
b1 $
1"
#27200
b10 $
0"
#27300
b0 $
1!
1"
#27400
b1 $
0"
#27500
b10 $
1"
#27600
b0 $
0!
0"
#27700
b1 $
1"
#27800
b10 $
0"
#27900
b0 $
1!
1"
#28000
b1 $
0"
#28100
b10 $
1"
#28200
b0 $
0!
0"
#28300
b1 $
1"
#28400
b10 $
0"
#28500
b0 $
1!
1"
#28600
b1 $
0"
#28700
b10 $
1"
#28800
b0 $
0!
0"
#28900
b1 $
1"
#29000
b10 $
0"
#29100
b0 $
1!
1"
#29200
b1 $
0"
#29300
b10 $
1"
#29400
b0 $
0!
0"
#29500
b1 $
1"
#29600
b10 $
0"
#29700
b0 $
1!
1"
#29800
b1 $
0"
#29900
b10 $
1"
#30000
b0 $
0!
0"
#30100
b1 $
1"
#30200
b10 $
0"
#30300
b0 $
1!
1"
#30400
b1 $
0"
#30500
b10 $
1"
#30600
b0 $
0!
0"
#30700
b1 $
1"
#30800
b10 $
0"
#30900
b0 $
1!
1"
#31000
b1 $
0"
#31100
b10 $
1"
